PandasExplorer/__init__.py
PandasExplorer/app.py
PandasDataExplorer-0.1.0.dist-info/LICENSE
PandasDataExplorer-0.1.0.dist-info/METADATA
PandasDataExplorer-0.1.0.dist-info/WHEEL
PandasDataExplorer-0.1.0.dist-info/top_level.txt
PandasDataExplorer-0.1.0.dist-info/RECORD
