Metadata-Version: 2.1
Name: PandasDataExplorer
Version: 0.1.0
Summary: A Python package for exploring and cleaning Pandas DataFrames
Author: Ankur Zalavadiya
Author-email: heyankur19@gmail.com
Classifier: Programming Language :: Python :: 3
Classifier: License :: OSI Approved :: MIT License
Classifier: Operating System :: OS Independent
Requires-Python: >=3.6
License-File: LICENSE
Requires-Dist: pandas>=1.2.0
Requires-Dist: ydata-profiling>=3.0.0
Requires-Dist: plotly>=5.0.0
